odoo/addons/biba_ardoak/__init__.py
odoo/addons/biba_ardoak/__manifest__.py
odoo/addons/biba_ardoak/data/ir_config_parameter.xml
odoo/addons/biba_ardoak/i18n/es.po
odoo/addons/biba_ardoak/i18n/eu_ES.po
odoo/addons/biba_ardoak/i18n/fr.po
odoo/addons/biba_ardoak/models/__init__.py
odoo/addons/biba_ardoak/models/account_invoice.py
odoo/addons/biba_ardoak/models/mail_thread.py
odoo/addons/biba_ardoak/models/product_template.py
odoo/addons/biba_ardoak/models/res_partner.py
odoo/addons/biba_ardoak/models/sale_order.py
odoo/addons/biba_ardoak/models/stock_picking_batch.py
odoo/addons/biba_ardoak/report/__init__.py
odoo/addons/biba_ardoak/report/account_invoice_report_view.xml
odoo/addons/biba_ardoak/report/delivery_note_mail_template.xml
odoo/addons/biba_ardoak/report/invoice_report.py
odoo/addons/biba_ardoak/report/report_delivery_document_note.xml
odoo/addons/biba_ardoak/report/report_picking_batch_delivery_note.xml
odoo/addons/biba_ardoak/report/sale_report.py
odoo/addons/biba_ardoak/report/stock_picking_batch_report_views.xml
odoo/addons/biba_ardoak/security/ir.model.access.csv
odoo/addons/biba_ardoak/views/product_template.xml
odoo/addons/biba_ardoak/views/report_invoice.xml
odoo/addons/biba_ardoak/views/report_view.xml
odoo/addons/biba_ardoak/views/res_partner.xml
odoo/addons/biba_ardoak/wizards/__init__.py
odoo/addons/biba_ardoak/wizards/stock_picking_batch/__init__.py
odoo/addons/biba_ardoak/wizards/stock_picking_batch/stock_picking_batch.xml
odoo14_addon_biba_ardoak-14.0.0.3.0.dist-info/METADATA
odoo14_addon_biba_ardoak-14.0.0.3.0.dist-info/WHEEL
odoo14_addon_biba_ardoak-14.0.0.3.0.dist-info/top_level.txt
odoo14_addon_biba_ardoak-14.0.0.3.0.dist-info/RECORD
